Metadata-Version: 1.1
Name: vintage
Version: 0.4.1
Summary: Python library for deprecating code
Home-page: https://github.com/getslash/vintage
Author: Slash Developers
Author-email: vmalloc@gmail.com
License: BSD3
Platform: UNKNOWN
Classifier: Programming Language :: Python :: 2.6
Classifier: Programming Language :: Python :: 2.7
Classifier: Programming Language :: Python :: 3.3
Classifier: Programming Language :: Python :: 3.4
Classifier: Programming Language :: Python :: 3.5
Classifier: Programming Language :: Python :: 3.6
